<?xml version="1.0" encoding="utf-8" ?>
<dwsync>
<file name="001_01.png" server="ftp.studiogilardi.it/www.studiogilardi.it/" local="129483018500000000" remote="129721474800000000" />
<file name="001_01_Grey.png" server="ftp.studiogilardi.it/www.studiogilardi.it/" local="129483018500000000" remote="129721474800000000" />
<file name="001_02.png" server="ftp.studiogilardi.it/www.studiogilardi.it/" local="129483018500000000" remote="129721474800000000" />
<file name="001_02_Grey.png" server="ftp.studiogilardi.it/www.studiogilardi.it/" local="129483018500000000" remote="129721474800000000" />
<file name="001_03.png" server="ftp.studiogilardi.it/www.studiogilardi.it/" local="129483018500000000" remote="129721474800000000" />
<file name="001_03_Grey.png" server="ftp.studiogilardi.it/www.studiogilardi.it/" local="129483018500000000" remote="129721474800000000" />
<file name="001_04.png" server="ftp.studiogilardi.it/www.studiogilardi.it/" local="129483018500000000" remote="129721474800000000" />
<file name="001_04_Grey.png" server="ftp.studiogilardi.it/www.studiogilardi.it/" local="129483018500000000" remote="129721474800000000" />
<file name="001_05.png" server="ftp.studiogilardi.it/www.studiogilardi.it/" local="129483018500000000" remote="129721474800000000" />
<file name="001_05_Grey.png" server="ftp.studiogilardi.it/www.studiogilardi.it/" local="129483018500000000" remote="129721474800000000" />
<file name="001_06.png" server="ftp.studiogilardi.it/www.studiogilardi.it/" local="129483018500000000" remote="129721474800000000" />
<file name="001_06_Grey.png" server="ftp.studiogilardi.it/www.studiogilardi.it/" local="129483018500000000" remote="129721474800000000" />
<file name="001_07.png" server="ftp.studiogilardi.it/www.studiogilardi.it/" local="129483018500000000" remote="129721474800000000" />
<file name="001_07_Grey.png" server="ftp.studiogilardi.it/www.studiogilardi.it/" local="129483018500000000" remote="129721474800000000" />
<file name="001_08.png" server="ftp.studiogilardi.it/www.studiogilardi.it/" local="129483018500000000" remote="129721474800000000" />
<file name="001_08_Grey.png" server="ftp.studiogilardi.it/www.studiogilardi.it/" local="129483018500000000" remote="129721474800000000" />
<file name="001_09.png" server="ftp.studiogilardi.it/www.studiogilardi.it/" local="129483018500000000" remote="129721474800000000" />
<file name="001_09_Grey.png" server="ftp.studiogilardi.it/www.studiogilardi.it/" local="129483018500000000" remote="129721474800000000" />
<file name="001_10.png" server="ftp.studiogilardi.it/www.studiogilardi.it/" local="129483018500000000" remote="129721474800000000" />
<file name="001_10_Grey.png" server="ftp.studiogilardi.it/www.studiogilardi.it/" local="129483018500000000" remote="129721474800000000" />
<file name="001_11.png" server="ftp.studiogilardi.it/www.studiogilardi.it/" local="129483018500000000" remote="129721474800000000" />
<file name="001_11_Grey.png" server="ftp.studiogilardi.it/www.studiogilardi.it/" local="129483018500000000" remote="129721474800000000" />
<file name="001_12.png" server="ftp.studiogilardi.it/www.studiogilardi.it/" local="129483018500000000" remote="129721474800000000" />
<file name="001_12_Grey.png" server="ftp.studiogilardi.it/www.studiogilardi.it/" local="129483018500000000" remote="129721474800000000" />
<file name="001_13.png" server="ftp.studiogilardi.it/www.studiogilardi.it/" local="129483018500000000" remote="129721474800000000" />
<file name="001_13_Grey.png" server="ftp.studiogilardi.it/www.studiogilardi.it/" local="129483018500000000" remote="129721474800000000" />
<file name="001_14.png" server="ftp.studiogilardi.it/www.studiogilardi.it/" local="129483018500000000" remote="129721474800000000" />
<file name="001_14_Grey.png" server="ftp.studiogilardi.it/www.studiogilardi.it/" local="129483018500000000" remote="129721474800000000" />
<file name="001_15.png" server="ftp.studiogilardi.it/www.studiogilardi.it/" local="129483018500000000" remote="129721474800000000" />
<file name="001_15_Grey.png" server="ftp.studiogilardi.it/www.studiogilardi.it/" local="129483018500000000" remote="129721474800000000" />
<file name="001_16.png" server="ftp.studiogilardi.it/www.studiogilardi.it/" local="129483018500000000" remote="129721474800000000" />
<file name="001_16_Grey.png" server="ftp.studiogilardi.it/www.studiogilardi.it/" local="129483018500000000" remote="129721474800000000" />
<file name="001_17.png" server="ftp.studiogilardi.it/www.studiogilardi.it/" local="129483018500000000" remote="129721474800000000" />
<file name="001_17_Grey.png" server="ftp.studiogilardi.it/www.studiogilardi.it/" local="129483018500000000" remote="129721474800000000" />
<file name="001_18.png" server="ftp.studiogilardi.it/www.studiogilardi.it/" local="129483018500000000" remote="129721474800000000" />
<file name="001_18_Grey.png" server="ftp.studiogilardi.it/www.studiogilardi.it/" local="129483018500000000" remote="129721474800000000" />
<file name="001_19.png" server="ftp.studiogilardi.it/www.studiogilardi.it/" local="129483018500000000" remote="129721474800000000" />
<file name="001_19_Grey.png" server="ftp.studiogilardi.it/www.studiogilardi.it/" local="129483018500000000" remote="129721474800000000" />
<file name="001_20.png" server="ftp.studiogilardi.it/www.studiogilardi.it/" local="129483018500000000" remote="129721474800000000" />
<file name="001_20_Grey.png" server="ftp.studiogilardi.it/www.studiogilardi.it/" local="129483018500000000" remote="129721474800000000" />
<file name="001_21.png" server="ftp.studiogilardi.it/www.studiogilardi.it/" local="129483018500000000" remote="129721474800000000" />
<file name="001_21_Grey.png" server="ftp.studiogilardi.it/www.studiogilardi.it/" local="129483018500000000" remote="129721474800000000" />
<file name="001_22.png" server="ftp.studiogilardi.it/www.studiogilardi.it/" local="129483018500000000" remote="129721474800000000" />
<file name="001_22_Grey.png" server="ftp.studiogilardi.it/www.studiogilardi.it/" local="129483018500000000" remote="129721474800000000" />
<file name="001_23.png" server="ftp.studiogilardi.it/www.studiogilardi.it/" local="129483018500000000" remote="129721474800000000" />
<file name="001_23_Grey.png" server="ftp.studiogilardi.it/www.studiogilardi.it/" local="129483018500000000" remote="129721474800000000" />
<file name="001_24.png" server="ftp.studiogilardi.it/www.studiogilardi.it/" local="129483018500000000" remote="129721474800000000" />
<file name="001_24_Grey.png" server="ftp.studiogilardi.it/www.studiogilardi.it/" local="129483018500000000" remote="129721474800000000" />
<file name="001_25.png" server="ftp.studiogilardi.it/www.studiogilardi.it/" local="129483018500000000" remote="129721474800000000" />
<file name="001_25_Grey.png" server="ftp.studiogilardi.it/www.studiogilardi.it/" local="129483018500000000" remote="129721474800000000" />
<file name="001_26.png" server="ftp.studiogilardi.it/www.studiogilardi.it/" local="129483018500000000" remote="129721474800000000" />
<file name="001_26_Grey.png" server="ftp.studiogilardi.it/www.studiogilardi.it/" local="129483018500000000" remote="129721474800000000" />
<file name="001_27.png" server="ftp.studiogilardi.it/www.studiogilardi.it/" local="129483018500000000" remote="129721474800000000" />
<file name="001_27_Grey.png" server="ftp.studiogilardi.it/www.studiogilardi.it/" local="129483018500000000" remote="129721474800000000" />
<file name="001_28.png" server="ftp.studiogilardi.it/www.studiogilardi.it/" local="129483018500000000" remote="129721474800000000" />
<file name="001_28_Grey.png" server="ftp.studiogilardi.it/www.studiogilardi.it/" local="129483018500000000" remote="129721474800000000" />
<file name="001_29.png" server="ftp.studiogilardi.it/www.studiogilardi.it/" local="129483018500000000" remote="129721474800000000" />
<file name="001_29_Grey.png" server="ftp.studiogilardi.it/www.studiogilardi.it/" local="129483018500000000" remote="129721474800000000" />
<file name="001_30.png" server="ftp.studiogilardi.it/www.studiogilardi.it/" local="129483018500000000" remote="129721474800000000" />
<file name="001_30_Grey.png" server="ftp.studiogilardi.it/www.studiogilardi.it/" local="129483018500000000" remote="129721474800000000" />
<file name="001_31.png" server="ftp.studiogilardi.it/www.studiogilardi.it/" local="129483018500000000" remote="129721474800000000" />
<file name="001_31_Grey.png" server="ftp.studiogilardi.it/www.studiogilardi.it/" local="129483018500000000" remote="129721474800000000" />
<file name="001_32.png" server="ftp.studiogilardi.it/www.studiogilardi.it/" local="129483018500000000" remote="129721474800000000" />
<file name="001_32_Grey.png" server="ftp.studiogilardi.it/www.studiogilardi.it/" local="129483018500000000" remote="129721474800000000" />
<file name="001_33.png" server="ftp.studiogilardi.it/www.studiogilardi.it/" local="129483018500000000" remote="129721474800000000" />
<file name="001_33_Grey.png" server="ftp.studiogilardi.it/www.studiogilardi.it/" local="129483018500000000" remote="129721474800000000" />
<file name="001_34.png" server="ftp.studiogilardi.it/www.studiogilardi.it/" local="129483018500000000" remote="129721474800000000" />
<file name="001_34_Grey.png" server="ftp.studiogilardi.it/www.studiogilardi.it/" local="129483018500000000" remote="129721474800000000" />
<file name="001_35.png" server="ftp.studiogilardi.it/www.studiogilardi.it/" local="129483018500000000" remote="129721474800000000" />
<file name="001_35_Grey.png" server="ftp.studiogilardi.it/www.studiogilardi.it/" local="129483018500000000" remote="129721474800000000" />
<file name="001_36.png" server="ftp.studiogilardi.it/www.studiogilardi.it/" local="129483018500000000" remote="129721474800000000" />
<file name="001_36_Grey.png" server="ftp.studiogilardi.it/www.studiogilardi.it/" local="129483018500000000" remote="129721474800000000" />
<file name="001_37.png" server="ftp.studiogilardi.it/www.studiogilardi.it/" local="129483018500000000" remote="129721474800000000" />
<file name="001_37_Grey.png" server="ftp.studiogilardi.it/www.studiogilardi.it/" local="129483018500000000" remote="129721474800000000" />
<file name="001_38.png" server="ftp.studiogilardi.it/www.studiogilardi.it/" local="129483018500000000" remote="129721474800000000" />
<file name="001_38_Grey.png" server="ftp.studiogilardi.it/www.studiogilardi.it/" local="129483018500000000" remote="129721474800000000" />
<file name="001_39.png" server="ftp.studiogilardi.it/www.studiogilardi.it/" local="129483018500000000" remote="129721474800000000" />
<file name="001_39_Grey.png" server="ftp.studiogilardi.it/www.studiogilardi.it/" local="129483018500000000" remote="129721474800000000" />
<file name="001_40.png" server="ftp.studiogilardi.it/www.studiogilardi.it/" local="129483018500000000" remote="129721474800000000" />
<file name="001_40_Grey.png" server="ftp.studiogilardi.it/www.studiogilardi.it/" local="129483018500000000" remote="129721474800000000" />
<file name="001_41.png" server="ftp.studiogilardi.it/www.studiogilardi.it/" local="129483018500000000" remote="129721474800000000" />
<file name="001_41_Grey.png" server="ftp.studiogilardi.it/www.studiogilardi.it/" local="129483018500000000" remote="129721474800000000" />
<file name="001_42.png" server="ftp.studiogilardi.it/www.studiogilardi.it/" local="129483018500000000" remote="129721474800000000" />
<file name="001_42_Grey.png" server="ftp.studiogilardi.it/www.studiogilardi.it/" local="129483018500000000" remote="129721474800000000" />
<file name="001_43.png" server="ftp.studiogilardi.it/www.studiogilardi.it/" local="129483018500000000" remote="129721474800000000" />
<file name="001_43_Grey.png" server="ftp.studiogilardi.it/www.studiogilardi.it/" local="129483018500000000" remote="129721474800000000" />
<file name="001_44.png" server="ftp.studiogilardi.it/www.studiogilardi.it/" local="129483018500000000" remote="129721474800000000" />
<file name="001_44_Grey.png" server="ftp.studiogilardi.it/www.studiogilardi.it/" local="129483018500000000" remote="129721474800000000" />
<file name="001_45.png" server="ftp.studiogilardi.it/www.studiogilardi.it/" local="129483018500000000" remote="129721474800000000" />
<file name="001_45_Grey.png" server="ftp.studiogilardi.it/www.studiogilardi.it/" local="129483018500000000" remote="129721474800000000" />
<file name="001_46.png" server="ftp.studiogilardi.it/www.studiogilardi.it/" local="129483018500000000" remote="129721474800000000" />
<file name="001_46_Grey.png" server="ftp.studiogilardi.it/www.studiogilardi.it/" local="129483018500000000" remote="129721474800000000" />
<file name="001_47.png" server="ftp.studiogilardi.it/www.studiogilardi.it/" local="129483018500000000" remote="129721474800000000" />
<file name="001_47_Grey.png" server="ftp.studiogilardi.it/www.studiogilardi.it/" local="129483018500000000" remote="129721474800000000" />
<file name="001_48.png" server="ftp.studiogilardi.it/www.studiogilardi.it/" local="129483018500000000" remote="129721474800000000" />
<file name="001_48_Grey.png" server="ftp.studiogilardi.it/www.studiogilardi.it/" local="129483018500000000" remote="129721474800000000" />
<file name="001_49.png" server="ftp.studiogilardi.it/www.studiogilardi.it/" local="129483018500000000" remote="129721474800000000" />
<file name="001_49_Grey.png" server="ftp.studiogilardi.it/www.studiogilardi.it/" local="129483018500000000" remote="129721474800000000" />
<file name="001_50.png" server="ftp.studiogilardi.it/www.studiogilardi.it/" local="129483018500000000" remote="129721474800000000" />
<file name="001_50_Grey.png" server="ftp.studiogilardi.it/www.studiogilardi.it/" local="129483018500000000" remote="129721474800000000" />
<file name="001_51.png" server="ftp.studiogilardi.it/www.studiogilardi.it/" local="129483018500000000" remote="129721474800000000" />
<file name="001_51_Grey.png" server="ftp.studiogilardi.it/www.studiogilardi.it/" local="129483018500000000" remote="129721474800000000" />
<file name="001_52.png" server="ftp.studiogilardi.it/www.studiogilardi.it/" local="129483018500000000" remote="129721474800000000" />
<file name="001_52_Grey.png" server="ftp.studiogilardi.it/www.studiogilardi.it/" local="129483018500000000" remote="129721474800000000" />
<file name="001_53.png" server="ftp.studiogilardi.it/www.studiogilardi.it/" local="129483018500000000" remote="129721474800000000" />
<file name="001_53_Grey.png" server="ftp.studiogilardi.it/www.studiogilardi.it/" local="129483018500000000" remote="129721474800000000" />
<file name="001_54.png" server="ftp.studiogilardi.it/www.studiogilardi.it/" local="129483018500000000" remote="129721474800000000" />
<file name="001_54_Grey.png" server="ftp.studiogilardi.it/www.studiogilardi.it/" local="129483018500000000" remote="129721474800000000" />
<file name="001_55.png" server="ftp.studiogilardi.it/www.studiogilardi.it/" local="129483018500000000" remote="129721474800000000" />
<file name="001_55_Grey.png" server="ftp.studiogilardi.it/www.studiogilardi.it/" local="129483018500000000" remote="129721474800000000" />
<file name="001_56.png" server="ftp.studiogilardi.it/www.studiogilardi.it/" local="129483018500000000" remote="129721474800000000" />
<file name="001_56_Grey.png" server="ftp.studiogilardi.it/www.studiogilardi.it/" local="129483018500000000" remote="129721474800000000" />
<file name="001_57.png" server="ftp.studiogilardi.it/www.studiogilardi.it/" local="129483018500000000" remote="129721474800000000" />
<file name="001_57_Grey.png" server="ftp.studiogilardi.it/www.studiogilardi.it/" local="129483018500000000" remote="129721474800000000" />
<file name="001_58.png" server="ftp.studiogilardi.it/www.studiogilardi.it/" local="129483018500000000" remote="129721474800000000" />
<file name="001_58_Grey.png" server="ftp.studiogilardi.it/www.studiogilardi.it/" local="129483018500000000" remote="129721474800000000" />
<file name="001_59.png" server="ftp.studiogilardi.it/www.studiogilardi.it/" local="129483018500000000" remote="129721474800000000" />
<file name="001_59_Grey.png" server="ftp.studiogilardi.it/www.studiogilardi.it/" local="129483018500000000" remote="129721474800000000" />
<file name="001_60.png" server="ftp.studiogilardi.it/www.studiogilardi.it/" local="129483018500000000" remote="129721474800000000" />
<file name="001_60_Grey.png" server="ftp.studiogilardi.it/www.studiogilardi.it/" local="129483018500000000" remote="129721474800000000" />
<file name="001_01.png" server="ftp.fiamsport.it/www.fiamsport.it/gare/" local="129483018500000000" remote="129911581800000000" />
<file name="001_01_Grey.png" server="ftp.fiamsport.it/www.fiamsport.it/gare/" local="129483018500000000" remote="129911581800000000" />
<file name="001_02.png" server="ftp.fiamsport.it/www.fiamsport.it/gare/" local="129483018500000000" remote="129911581800000000" />
<file name="001_02_Grey.png" server="ftp.fiamsport.it/www.fiamsport.it/gare/" local="129483018500000000" remote="129911581800000000" />
<file name="001_03.png" server="ftp.fiamsport.it/www.fiamsport.it/gare/" local="129483018500000000" remote="129911581800000000" />
<file name="001_03_Grey.png" server="ftp.fiamsport.it/www.fiamsport.it/gare/" local="129483018500000000" remote="129911581800000000" />
<file name="001_04.png" server="ftp.fiamsport.it/www.fiamsport.it/gare/" local="129483018500000000" remote="129911581800000000" />
<file name="001_04_Grey.png" server="ftp.fiamsport.it/www.fiamsport.it/gare/" local="129483018500000000" remote="129911581800000000" />
<file name="001_05.png" server="ftp.fiamsport.it/www.fiamsport.it/gare/" local="129483018500000000" remote="129911581800000000" />
<file name="001_05_Grey.png" server="ftp.fiamsport.it/www.fiamsport.it/gare/" local="129483018500000000" remote="129911581800000000" />
<file name="001_06.png" server="ftp.fiamsport.it/www.fiamsport.it/gare/" local="129483018500000000" remote="129911581800000000" />
<file name="001_06_Grey.png" server="ftp.fiamsport.it/www.fiamsport.it/gare/" local="129483018500000000" remote="129911581800000000" />
<file name="001_07.png" server="ftp.fiamsport.it/www.fiamsport.it/gare/" local="129483018500000000" remote="129911581800000000" />
<file name="001_07_Grey.png" server="ftp.fiamsport.it/www.fiamsport.it/gare/" local="129483018500000000" remote="129911581800000000" />
<file name="001_08.png" server="ftp.fiamsport.it/www.fiamsport.it/gare/" local="129483018500000000" remote="129911581800000000" />
<file name="001_08_Grey.png" server="ftp.fiamsport.it/www.fiamsport.it/gare/" local="129483018500000000" remote="129911581800000000" />
<file name="001_09.png" server="ftp.fiamsport.it/www.fiamsport.it/gare/" local="129483018500000000" remote="129911581800000000" />
<file name="001_09_Grey.png" server="ftp.fiamsport.it/www.fiamsport.it/gare/" local="129483018500000000" remote="129911581800000000" />
<file name="001_10.png" server="ftp.fiamsport.it/www.fiamsport.it/gare/" local="129483018500000000" remote="129911581800000000" />
<file name="001_10_Grey.png" server="ftp.fiamsport.it/www.fiamsport.it/gare/" local="129483018500000000" remote="129911581800000000" />
<file name="001_11.png" server="ftp.fiamsport.it/www.fiamsport.it/gare/" local="129483018500000000" remote="129911581800000000" />
<file name="001_11_Grey.png" server="ftp.fiamsport.it/www.fiamsport.it/gare/" local="129483018500000000" remote="129911581800000000" />
<file name="001_12.png" server="ftp.fiamsport.it/www.fiamsport.it/gare/" local="129483018500000000" remote="129911581800000000" />
<file name="001_12_Grey.png" server="ftp.fiamsport.it/www.fiamsport.it/gare/" local="129483018500000000" remote="129911581800000000" />
<file name="001_13.png" server="ftp.fiamsport.it/www.fiamsport.it/gare/" local="129483018500000000" remote="129911581800000000" />
<file name="001_13_Grey.png" server="ftp.fiamsport.it/www.fiamsport.it/gare/" local="129483018500000000" remote="129911581800000000" />
<file name="001_14.png" server="ftp.fiamsport.it/www.fiamsport.it/gare/" local="129483018500000000" remote="129911581800000000" />
<file name="001_14_Grey.png" server="ftp.fiamsport.it/www.fiamsport.it/gare/" local="129483018500000000" remote="129911581800000000" />
<file name="001_15.png" server="ftp.fiamsport.it/www.fiamsport.it/gare/" local="129483018500000000" remote="129911581800000000" />
<file name="001_15_Grey.png" server="ftp.fiamsport.it/www.fiamsport.it/gare/" local="129483018500000000" remote="129911581800000000" />
<file name="001_16.png" server="ftp.fiamsport.it/www.fiamsport.it/gare/" local="129483018500000000" remote="129911581800000000" />
<file name="001_16_Grey.png" server="ftp.fiamsport.it/www.fiamsport.it/gare/" local="129483018500000000" remote="129911581800000000" />
<file name="001_17.png" server="ftp.fiamsport.it/www.fiamsport.it/gare/" local="129483018500000000" remote="129911581800000000" />
<file name="001_17_Grey.png" server="ftp.fiamsport.it/www.fiamsport.it/gare/" local="129483018500000000" remote="129911581800000000" />
<file name="001_18.png" server="ftp.fiamsport.it/www.fiamsport.it/gare/" local="129483018500000000" remote="129911581800000000" />
<file name="001_18_Grey.png" server="ftp.fiamsport.it/www.fiamsport.it/gare/" local="129483018500000000" remote="129911581800000000" />
<file name="001_19.png" server="ftp.fiamsport.it/www.fiamsport.it/gare/" local="129483018500000000" remote="129911581800000000" />
<file name="001_19_Grey.png" server="ftp.fiamsport.it/www.fiamsport.it/gare/" local="129483018500000000" remote="129911581800000000" />
<file name="001_20.png" server="ftp.fiamsport.it/www.fiamsport.it/gare/" local="129483018500000000" remote="129911581800000000" />
<file name="001_20_Grey.png" server="ftp.fiamsport.it/www.fiamsport.it/gare/" local="129483018500000000" remote="129911581800000000" />
<file name="001_21.png" server="ftp.fiamsport.it/www.fiamsport.it/gare/" local="129483018500000000" remote="129911581800000000" />
<file name="001_21_Grey.png" server="ftp.fiamsport.it/www.fiamsport.it/gare/" local="129483018500000000" remote="129911581800000000" />
<file name="001_22.png" server="ftp.fiamsport.it/www.fiamsport.it/gare/" local="129483018500000000" remote="129911581800000000" />
<file name="001_22_Grey.png" server="ftp.fiamsport.it/www.fiamsport.it/gare/" local="129483018500000000" remote="129911581800000000" />
<file name="001_23.png" server="ftp.fiamsport.it/www.fiamsport.it/gare/" local="129483018500000000" remote="129911581800000000" />
<file name="001_23_Grey.png" server="ftp.fiamsport.it/www.fiamsport.it/gare/" local="129483018500000000" remote="129911581800000000" />
<file name="001_24.png" server="ftp.fiamsport.it/www.fiamsport.it/gare/" local="129483018500000000" remote="129911581800000000" />
<file name="001_24_Grey.png" server="ftp.fiamsport.it/www.fiamsport.it/gare/" local="129483018500000000" remote="129911581800000000" />
<file name="001_25.png" server="ftp.fiamsport.it/www.fiamsport.it/gare/" local="129483018500000000" remote="129911581800000000" />
<file name="001_25_Grey.png" server="ftp.fiamsport.it/www.fiamsport.it/gare/" local="129483018500000000" remote="129911581800000000" />
<file name="001_26.png" server="ftp.fiamsport.it/www.fiamsport.it/gare/" local="129483018500000000" remote="129911581800000000" />
<file name="001_26_Grey.png" server="ftp.fiamsport.it/www.fiamsport.it/gare/" local="129483018500000000" remote="129911581800000000" />
<file name="001_27.png" server="ftp.fiamsport.it/www.fiamsport.it/gare/" local="129483018500000000" remote="129911581800000000" />
<file name="001_27_Grey.png" server="ftp.fiamsport.it/www.fiamsport.it/gare/" local="129483018500000000" remote="129911581800000000" />
<file name="001_28.png" server="ftp.fiamsport.it/www.fiamsport.it/gare/" local="129483018500000000" remote="129911581800000000" />
<file name="001_28_Grey.png" server="ftp.fiamsport.it/www.fiamsport.it/gare/" local="129483018500000000" remote="129911581800000000" />
<file name="001_29.png" server="ftp.fiamsport.it/www.fiamsport.it/gare/" local="129483018500000000" remote="129911581800000000" />
<file name="001_29_Grey.png" server="ftp.fiamsport.it/www.fiamsport.it/gare/" local="129483018500000000" remote="129911581800000000" />
<file name="001_30.png" server="ftp.fiamsport.it/www.fiamsport.it/gare/" local="129483018500000000" remote="129911581800000000" />
<file name="001_30_Grey.png" server="ftp.fiamsport.it/www.fiamsport.it/gare/" local="129483018500000000" remote="129911581800000000" />
<file name="001_31.png" server="ftp.fiamsport.it/www.fiamsport.it/gare/" local="129483018500000000" remote="129911581800000000" />
<file name="001_31_Grey.png" server="ftp.fiamsport.it/www.fiamsport.it/gare/" local="129483018500000000" remote="129911581800000000" />
<file name="001_32.png" server="ftp.fiamsport.it/www.fiamsport.it/gare/" local="129483018500000000" remote="129911581800000000" />
<file name="001_32_Grey.png" server="ftp.fiamsport.it/www.fiamsport.it/gare/" local="129483018500000000" remote="129911581800000000" />
<file name="001_33.png" server="ftp.fiamsport.it/www.fiamsport.it/gare/" local="129483018500000000" remote="129911581800000000" />
<file name="001_33_Grey.png" server="ftp.fiamsport.it/www.fiamsport.it/gare/" local="129483018500000000" remote="129911581800000000" />
<file name="001_34.png" server="ftp.fiamsport.it/www.fiamsport.it/gare/" local="129483018500000000" remote="129911581800000000" />
<file name="001_34_Grey.png" server="ftp.fiamsport.it/www.fiamsport.it/gare/" local="129483018500000000" remote="129911581800000000" />
<file name="001_35.png" server="ftp.fiamsport.it/www.fiamsport.it/gare/" local="129483018500000000" remote="129911581800000000" />
<file name="001_35_Grey.png" server="ftp.fiamsport.it/www.fiamsport.it/gare/" local="129483018500000000" remote="129911581800000000" />
<file name="001_36.png" server="ftp.fiamsport.it/www.fiamsport.it/gare/" local="129483018500000000" remote="129911581800000000" />
<file name="001_36_Grey.png" server="ftp.fiamsport.it/www.fiamsport.it/gare/" local="129483018500000000" remote="129911581800000000" />
<file name="001_37.png" server="ftp.fiamsport.it/www.fiamsport.it/gare/" local="129483018500000000" remote="129911581800000000" />
<file name="001_37_Grey.png" server="ftp.fiamsport.it/www.fiamsport.it/gare/" local="129483018500000000" remote="129911581800000000" />
<file name="001_38.png" server="ftp.fiamsport.it/www.fiamsport.it/gare/" local="129483018500000000" remote="129911581800000000" />
<file name="001_38_Grey.png" server="ftp.fiamsport.it/www.fiamsport.it/gare/" local="129483018500000000" remote="129911581800000000" />
<file name="001_39.png" server="ftp.fiamsport.it/www.fiamsport.it/gare/" local="129483018500000000" remote="129911581800000000" />
<file name="001_39_Grey.png" server="ftp.fiamsport.it/www.fiamsport.it/gare/" local="129483018500000000" remote="129911581800000000" />
<file name="001_40.png" server="ftp.fiamsport.it/www.fiamsport.it/gare/" local="129483018500000000" remote="129911581800000000" />
<file name="001_40_Grey.png" server="ftp.fiamsport.it/www.fiamsport.it/gare/" local="129483018500000000" remote="129911581800000000" />
<file name="001_41.png" server="ftp.fiamsport.it/www.fiamsport.it/gare/" local="129483018500000000" remote="129911581800000000" />
<file name="001_41_Grey.png" server="ftp.fiamsport.it/www.fiamsport.it/gare/" local="129483018500000000" remote="129911581800000000" />
<file name="001_42.png" server="ftp.fiamsport.it/www.fiamsport.it/gare/" local="129483018500000000" remote="129911581800000000" />
<file name="001_42_Grey.png" server="ftp.fiamsport.it/www.fiamsport.it/gare/" local="129483018500000000" remote="129911581800000000" />
<file name="001_43.png" server="ftp.fiamsport.it/www.fiamsport.it/gare/" local="129483018500000000" remote="129911581800000000" />
<file name="001_43_Grey.png" server="ftp.fiamsport.it/www.fiamsport.it/gare/" local="129483018500000000" remote="129911581800000000" />
<file name="001_44.png" server="ftp.fiamsport.it/www.fiamsport.it/gare/" local="129483018500000000" remote="129911581800000000" />
<file name="001_44_Grey.png" server="ftp.fiamsport.it/www.fiamsport.it/gare/" local="129483018500000000" remote="129911581800000000" />
<file name="001_45.png" server="ftp.fiamsport.it/www.fiamsport.it/gare/" local="129483018500000000" remote="129911581800000000" />
<file name="001_45_Grey.png" server="ftp.fiamsport.it/www.fiamsport.it/gare/" local="129483018500000000" remote="129911581800000000" />
<file name="001_46.png" server="ftp.fiamsport.it/www.fiamsport.it/gare/" local="129483018500000000" remote="129911581800000000" />
<file name="001_46_Grey.png" server="ftp.fiamsport.it/www.fiamsport.it/gare/" local="129483018500000000" remote="129911581800000000" />
<file name="001_47.png" server="ftp.fiamsport.it/www.fiamsport.it/gare/" local="129483018500000000" remote="129911581800000000" />
<file name="001_47_Grey.png" server="ftp.fiamsport.it/www.fiamsport.it/gare/" local="129483018500000000" remote="129911581800000000" />
<file name="001_48.png" server="ftp.fiamsport.it/www.fiamsport.it/gare/" local="129483018500000000" remote="129911581800000000" />
<file name="001_48_Grey.png" server="ftp.fiamsport.it/www.fiamsport.it/gare/" local="129483018500000000" remote="129911581800000000" />
<file name="001_49.png" server="ftp.fiamsport.it/www.fiamsport.it/gare/" local="129483018500000000" remote="129911581800000000" />
<file name="001_49_Grey.png" server="ftp.fiamsport.it/www.fiamsport.it/gare/" local="129483018500000000" remote="129911581800000000" />
<file name="001_50.png" server="ftp.fiamsport.it/www.fiamsport.it/gare/" local="129483018500000000" remote="129911581800000000" />
<file name="001_50_Grey.png" server="ftp.fiamsport.it/www.fiamsport.it/gare/" local="129483018500000000" remote="129911581800000000" />
<file name="001_51.png" server="ftp.fiamsport.it/www.fiamsport.it/gare/" local="129483018500000000" remote="129911581800000000" />
<file name="001_51_Grey.png" server="ftp.fiamsport.it/www.fiamsport.it/gare/" local="129483018500000000" remote="129911581800000000" />
<file name="001_52.png" server="ftp.fiamsport.it/www.fiamsport.it/gare/" local="129483018500000000" remote="129911581800000000" />
<file name="001_52_Grey.png" server="ftp.fiamsport.it/www.fiamsport.it/gare/" local="129483018500000000" remote="129911581800000000" />
<file name="001_53.png" server="ftp.fiamsport.it/www.fiamsport.it/gare/" local="129483018500000000" remote="129911581800000000" />
<file name="001_53_Grey.png" server="ftp.fiamsport.it/www.fiamsport.it/gare/" local="129483018500000000" remote="129911581800000000" />
<file name="001_54.png" server="ftp.fiamsport.it/www.fiamsport.it/gare/" local="129483018500000000" remote="129911581800000000" />
<file name="001_54_Grey.png" server="ftp.fiamsport.it/www.fiamsport.it/gare/" local="129483018500000000" remote="129911581800000000" />
<file name="001_55.png" server="ftp.fiamsport.it/www.fiamsport.it/gare/" local="129483018500000000" remote="129911581800000000" />
<file name="001_55_Grey.png" server="ftp.fiamsport.it/www.fiamsport.it/gare/" local="129483018500000000" remote="129911582400000000" />
<file name="001_56.png" server="ftp.fiamsport.it/www.fiamsport.it/gare/" local="129483018500000000" remote="129911582400000000" />
<file name="001_56_Grey.png" server="ftp.fiamsport.it/www.fiamsport.it/gare/" local="129483018500000000" remote="129911582400000000" />
<file name="001_57.png" server="ftp.fiamsport.it/www.fiamsport.it/gare/" local="129483018500000000" remote="129911582400000000" />
<file name="001_57_Grey.png" server="ftp.fiamsport.it/www.fiamsport.it/gare/" local="129483018500000000" remote="129911582400000000" />
<file name="001_58.png" server="ftp.fiamsport.it/www.fiamsport.it/gare/" local="129483018500000000" remote="129911582400000000" />
<file name="001_58_Grey.png" server="ftp.fiamsport.it/www.fiamsport.it/gare/" local="129483018500000000" remote="129911582400000000" />
<file name="001_59.png" server="ftp.fiamsport.it/www.fiamsport.it/gare/" local="129483018500000000" remote="129911582400000000" />
<file name="001_59_Grey.png" server="ftp.fiamsport.it/www.fiamsport.it/gare/" local="129483018500000000" remote="129911582400000000" />
<file name="001_60.png" server="ftp.fiamsport.it/www.fiamsport.it/gare/" local="129483018500000000" remote="129911582400000000" />
<file name="001_60_Grey.png" server="ftp.fiamsport.it/www.fiamsport.it/gare/" local="129483018500000000" remote="129911582400000000" />
<file name="acorbat_15.gif" server="ftp.fiamsport.it/www.fiamsport.it/gare/" local="128269749279199711" remote="129911582400000000" />
<file name="default.png" server="ftp.fiamsport.it/www.fiamsport.it/gare/" local="128363899915468750" remote="129911582400000000" />
<file name="excel.gif" server="ftp.fiamsport.it/www.fiamsport.it/gare/" local="128269787413515616" remote="129911582400000000" />
<file name="excel_15.gif" server="ftp.fiamsport.it/www.fiamsport.it/gare/" local="128269750849176020" remote="129911582400000000" />
<file name="image.gif" server="ftp.fiamsport.it/www.fiamsport.it/gare/" local="128269810485106686" remote="129911582400000000" />
<file name="images.gif" server="ftp.fiamsport.it/www.fiamsport.it/gare/" local="129851821668048319" remote="129911582400000000" />
<file name="PDF.gif" server="ftp.fiamsport.it/www.fiamsport.it/gare/" local="128269788385898432" remote="129911582400000000" />
<file name="PDF_15.gif" server="ftp.fiamsport.it/www.fiamsport.it/gare/" local="128269821322320316" remote="129911582400000000" />
<file name="PP.gif" server="ftp.fiamsport.it/www.fiamsport.it/gare/" local="128269787916953120" remote="129911582400000000" />
<file name="printmgr.png" server="ftp.fiamsport.it/www.fiamsport.it/gare/" local="127548997760000000" remote="129911582400000000" />
<file name="Word.gif" server="ftp.fiamsport.it/www.fiamsport.it/gare/" local="128269787097539072" remote="129911582400000000" />
<file name="word_15.gif" server="ftp.fiamsport.it/www.fiamsport.it/gare/" local="128269749707031248" remote="129911582400000000" />
<file name="zip.gif" server="ftp.fiamsport.it/www.fiamsport.it/gare/" local="128554063200000000" remote="129911582400000000" />
</dwsync>